smm_client/__about__.py
smm_client/__init__.py
smm_client/assets.py
smm_client/connection.py
smm_client/geometry.py
smm_client/missions.py
smm_client/organizations.py
smm_client/search.py
smm_client/types.py
smm_client-0.0.15.dist-info/METADATA
smm_client-0.0.15.dist-info/WHEEL
smm_client-0.0.15.dist-info/licenses/LICENSE.txt
smm_client-0.0.15.dist-info/RECORD
